{"cameraMode":{"drawMode":0,"name":"Shaded","section":"Shading Mode"},"sceneLighting":true,"audioPlay":false,"sceneViewState":{"showFog":true,"showMaterialUpdate":false,"showSkybox":true,"showFlares":true,"showImageEffects":true,"showParticleSystems":true},"in2DMode":false,"pivot":{"x":0.968597412109375,"y":0.792597770690918,"z":-21.994810104370118},"rotation":{"x":0.12709259986877442,"y":-0.8581196665763855,"z":0.25439608097076418,"w":0.42782896757125857},"size":0.036592911928892139,"orthographic":false}